my_timer/__init__.py
my_timer/timer.py
my_timer_daniel-0.1.1.dist-info/METADATA
my_timer_daniel-0.1.1.dist-info/WHEEL
my_timer_daniel-0.1.1.dist-info/top_level.txt
my_timer_daniel-0.1.1.dist-info/RECORD
